mh_llm/__init__.py
mh_llm/mh_llm.py
mh_llm/vllm/__init__.py
mh_llm/vllm/llm.py
mh_llm/vllm/logprobs.py
mh_llm/vllm/model_runner.py
mh_llm/vllm/output_processor.py
mh_llm/vllm/outputs.py
mh_llm/vllm/sampler.py
mh_llm/vllm/sampling_params.py
mh_llm/vllm/scheduler.py
mh_llm/vllm/utils.py
mh_llm/vllm/worker.py
mh_llm-0.0.1.dist-info/METADATA
mh_llm-0.0.1.dist-info/WHEEL
mh_llm-0.0.1.dist-info/licenses/LICENSE
mh_llm-0.0.1.dist-info/RECORD
