Metadata-Version: 2.4
Name: mh_llm
Version: 0.0.1
Summary: A Metropolis-Hastings based sampling framework for LLMs.
License: MIT
License-File: LICENSE
Author: Max Zuo
Author-email: zuo@brown.edu
Requires-Python: >=3.10,<4.0
Classifier: License :: OSI Approved :: MIT License
Classifier: Programming Language :: Python :: 3
Classifier: Programming Language :: Python :: 3.10
Classifier: Programming Language :: Python :: 3.11
Classifier: Programming Language :: Python :: 3.12
Classifier: Programming Language :: Python :: 3.13
Classifier: Programming Language :: Python :: 3.14
Requires-Dist: vllm (>=0.11.0)
